{
  "whale_alerts": [
    {
      "symbol": "BTC",
      "amount": 2500,
      "amount_usd": 325000000,
      "from": "Unknown Wallet",
      "to": "Binance",
      "from_type": "unknown",
      "to_type": "exchange",
      "timestamp": 1774108736
    },
    {
      "symbol": "BTC",
      "amount": 1200,
      "amount_usd": 156000000,
      "from": "Kraken",
      "to": "Unknown Wallet",
      "from_type": "exchange",
      "to_type": "unknown",
      "timestamp": 1774107956
    },
    {
      "symbol": "USDT",
      "amount": 120000000,
      "amount_usd": 120000000,
      "from": "Unknown Wallet",
      "to": "Bybit",
      "from_type": "unknown",
      "to_type": "exchange",
      "timestamp": 1774107056
    },
    {
      "symbol": "BTC",
      "amount": 800,
      "amount_usd": 104000000,
      "from": "Unknown Wallet",
      "to": "Upbit",
      "from_type": "unknown",
      "to_type": "exchange",
      "timestamp": 1774107356
    },
    {
      "symbol": "USDT",
      "amount": 80000000,
      "amount_usd": 80000000,
      "from": "Tether Treasury",
      "to": "Binance",
      "from_type": "unknown",
      "to_type": "exchange",
      "timestamp": 1774108256
    },
    {
      "symbol": "ETH",
      "amount": 15000,
      "amount_usd": 52500000,
      "from": "Unknown Wallet",
      "to": "Coinbase",
      "from_type": "unknown",
      "to_type": "exchange",
      "timestamp": 1774108556
    },
    {
      "symbol": "USDC",
      "amount": 45000000,
      "amount_usd": 45000000,
      "from": "Circle",
      "to": "Coinbase",
      "from_type": "unknown",
      "to_type": "exchange",
      "timestamp": 1774107656
    }
  ],
  "stablecoin_inflow": {
    "usdt": 200000000,
    "usdc": 45000000,
    "total": 245000000,
    "max_reference": 500000000
  },
  "mvrv": {
    "value": 2.08,
    "analysis": "MVRV <span style=\"color:var(--green)\">2.08</span> — 건강한 상승 구간. 홀더 대부분 소폭 수익. 목성(게자리) 확장 에너지 아래 점진적 상승 트렌드 유지 가능."
  },
  "cvd": {
    "total": -55545315,
    "whale": -30323809,
    "shark": -14123439,
    "fish": 8267100,
    "shrimp": -19365167,
    "buy_volume": 141736108,
    "sell_volume": 134973336,
    "btc_price": 70000,
    "trade_count": 1000,
    "source": "Demo (Binance 연결 대기)",
    "analysis": "<span style=\"color:var(--red)\">전체 매도 우세</span> — 총 CVD $-55.5M. 매도 압력 지속 중. 관망 권장."
  },
  "last_updated": "2026-03-21T16:00:56.130774+00:00",
  "analysis": "에너지 레벨: <span style='color:var(--gold)'>고에너지</span> — <span style=\"color:var(--gold)\">목성(게자리)</span>의 확장 에너지 아래 기관급 자금이 활발히 이동하고 있습니다. 스테이블코인 총 유입 <span style='color:var(--cyan)'>$245M</span>. 거래소 순유입 우세 → 단기 매도 압력 가능성에 주의하세요."
}